amulet_editor/__init__.py
amulet_editor/__main__.py
amulet_editor/_version.py
amulet_editor/__pyinstaller/__init__.py
amulet_editor/__pyinstaller/hook-OpenGL.py
amulet_editor/__pyinstaller/hook-PySide6.py
amulet_editor/__pyinstaller/hook-amulet_editor.py
amulet_editor/application/__init__.py
amulet_editor/application/_app.py
amulet_editor/application/_cli.py
amulet_editor/application/_invoke.py
amulet_editor/application/_main.py
amulet_editor/application/_splash/__init__.py
amulet_editor/application/_splash/_splash.py
amulet_editor/application/appearance/__init__.py
amulet_editor/application/appearance/_theme.py
amulet_editor/application/appearance/_theme_manager.py
amulet_editor/application/windows_/__init__.py
amulet_editor/application/windows_/_amulet_window.py
amulet_editor/application/windows_/_amulet_landing_window/__init__.py
amulet_editor/application/windows_/_amulet_landing_window/_landing_window.py
amulet_editor/application/windows_/_amulet_landing_window/_view.py
amulet_editor/application/windows_/_amulet_landing_window/views/__init__.py
amulet_editor/application/windows_/_amulet_landing_window/views/home/__init__.py
amulet_editor/application/windows_/_amulet_landing_window/views/home/home/__init__.py
amulet_editor/application/windows_/_amulet_landing_window/views/home/home/_home.py
amulet_editor/application/windows_/_amulet_landing_window/views/home/open_world/__init__.py
amulet_editor/application/windows_/_amulet_landing_window/views/home/open_world/_open_world.py
amulet_editor/data/__init__.py
amulet_editor/data/_rpc.py
amulet_editor/data/_localisation/__init__.py
amulet_editor/data/build/__init__.py
amulet_editor/data/build/_resources.py
amulet_editor/data/dev/__init__.py
amulet_editor/data/dev/_debug.py
amulet_editor/data/minecraft/__init__.py
amulet_editor/data/minecraft/_directory.py
amulet_editor/data/minecraft/_saves.py
amulet_editor/data/packages/__init__.py
amulet_editor/data/packages/_cache.py
amulet_editor/data/packages/_manage.py
amulet_editor-1.0.0a15.dist-info/METADATA
amulet_editor-1.0.0a15.dist-info/WHEEL
amulet_editor-1.0.0a15.dist-info/entry_points.txt
amulet_editor-1.0.0a15.dist-info/top_level.txt
amulet_editor-1.0.0a15.dist-info/RECORD
